genome_info/README.md
genome_info/__init__.py
genome_info/core/info.py
genome_info/core/utilities.py
genome_info/genomes/base/__init__.py
genome_info/genomes/data/__init__.py
genome_info/genomes/download.py
genome_info/genomes/genomes.py
genome_info/genomes/readers.py
genome_info/kmers/2bit.c
genome_info/kmers/2bit.h
genome_info/kmers/__init__.py
genome_info/kmers/interval_kmer.c
genome_info/kmers/interval_kmer.h
genome_info/kmers/kmer_reader.c
genome_info/kmers/kmer_reader.cpython-312-darwin.so
genome_info/kmers/kmer_reader.pxd
genome_info/kmers/kmer_reader.pyx
genome_info-1.0.8.dist-info/LICENSE.md
genome_info-1.0.8.dist-info/METADATA
genome_info-1.0.8.dist-info/WHEEL
genome_info-1.0.8.dist-info/RECORD
