Metadata-Version: 2.1
Name: genome_info
Version: 1.0.8
Summary: Python package genome annotations
Home-page: https://github.com/kylessmith/genome_info
License: GPL-2.0-or-later
Keywords: cython,annotation,genome
Author: Kyle S. Smith
Author-email: kyle.smith@stjude.org
Maintainer: Kyle S. Smith
Maintainer-email: kyle.smith@stjude.org
Requires-Python: >=3.10
Classifier: Development Status :: 4 - Beta
Classifier: Environment :: Console
Classifier: Intended Audience :: Developers
Classifier: Intended Audience :: Science/Research
Classifier: License :: OSI Approved :: GNU General Public License v2 or later (GPLv2+)
Classifier: Operating System :: POSIX :: Linux
Classifier: Programming Language :: Cython
Classifier: Programming Language :: Python
Classifier: Programming Language :: Python :: 3
Classifier: Programming Language :: Python :: 3.10
Classifier: Programming Language :: Python :: 3.11
Classifier: Programming Language :: Python :: 3.12
Classifier: Programming Language :: Python :: 3.6
Classifier: Topic :: Scientific/Engineering
Classifier: Topic :: Scientific/Engineering :: Bio-Informatics
Classifier: Topic :: Scientific/Engineering :: Mathematics
Classifier: Topic :: Software Development :: Libraries
Classifier: Topic :: Software Development :: Libraries :: Python Modules
Requires-Dist: cython (>=3.0.0,<4.0.0)
Requires-Dist: intervalframe (>=1.1.11,<2.0.0)
Requires-Dist: numpy (>=1.23.5)
Requires-Dist: pandas (>=2.0.0,<3.0.0)
Requires-Dist: tqdm (>=4.65.0,<5.0.0)
Project-URL: Documentation, https://www.biosciencestack.com/static/genome_info/docs/index.html
Project-URL: Repository, https://github.com/kylessmith/genome_info
